tools4yolo/README.MD
tools4yolo/__init__.py
tools4yolo/requirements.txt
tools4yolo/thirdparty.json
tools4yolo-0.11.dist-info/LICENSE.rst
tools4yolo-0.11.dist-info/METADATA
tools4yolo-0.11.dist-info/WHEEL
tools4yolo-0.11.dist-info/top_level.txt
tools4yolo-0.11.dist-info/RECORD
