Metadata-Version: 2.1
Name: tools4yolo
Version: 0.11
Summary: Some image augmentation tools for yolov5 (and probably other models)
Home-page: https://github.com/hansalemaos/tools4yolo
Author: Johannes Fischer
Author-email: aulasparticularesdealemaosp@gmail.com
License: MIT
Keywords: image,augmentation,yolov5,yolo
Classifier: Development Status :: 4 - Beta
Classifier: Programming Language :: Python :: 3 :: Only
Classifier: Programming Language :: Python :: 3.10
Classifier: Topic :: Software Development :: Libraries :: Python Modules
Classifier: Topic :: Utilities
License-File: LICENSE.rst
Requires-Dist: PILasOPENCV
Requires-Dist: Pillow
Requires-Dist: a-cv2-easy-resize
Requires-Dist: a-cv-imwrite-imread-plus
Requires-Dist: deepcopyall
Requires-Dist: fast-color-checker
Requires-Dist: flatten-any-dict-iterable-or-whatsoever
Requires-Dist: get-rectangle-infos
Requires-Dist: getpartofimg
Requires-Dist: list-all-files-recursively
Requires-Dist: numexpr
Requires-Dist: numpy
Requires-Dist: opencv-python
Requires-Dist: pandas
Requires-Dist: regex
Requires-Dist: rembg
Requires-Dist: scikit-learn
Requires-Dist: torch
